autoasd/__main__.py
autoasd/asd_controls.py
autoasd/spectralon_corrector.py
autoasd/img2/optimizing.png
autoasd/img2/rs3adjustconfig.png
autoasd/img2/rs3adjustconfig2.png
autoasd/img2/rs3control.png
autoasd/img2/rs3control2.png
autoasd/img2/rs3display.png
autoasd/img2/rs3displaygray.png
autoasd/img2/rs3instrumentcontrol.png
autoasd/img2/rs3instrumentcontrol2.png
autoasd/img2/rs3menu.png
autoasd/img2/rs3ok.png
autoasd/img2/rs3ok2.png
autoasd/img2/rs3specsave.png
autoasd/img2/rs3specsave2.png
autoasd/img2/status_color.png
autoasd/img2/white_status.png
autoasd/spectralon_data/spec_correction_i0.csv
autoasd/spectralon_data/spec_correction_i0_405nm.csv
autoasd/spectralon_data/spec_correction_i0_off_plane.csv
autoasd/spectralon_data/spec_correction_i30.csv
autoasd/spectralon_data/spec_correction_i45.csv
autoasd/spectralon_data/spec_correction_i60.csv
autoasd/spectralon_data/spec_correction_i60_405nm.csv
autoasd/spectralon_data/spec_correction_i60_off_plane.csv
AutoAsd-0.2.9.dist-info/METADATA
AutoAsd-0.2.9.dist-info/WHEEL
AutoAsd-0.2.9.dist-info/top_level.txt
AutoAsd-0.2.9.dist-info/RECORD
