Metadata-Version: 2.1
Name: AutoAsd
Version: 0.2.9
Summary: Automation script for ASD spectroscopy software.
Home-page: https://github.com/kathleenhoza/autoasd
Author: Kathleen Hoza
Author-email: hozak@wwu.edu
License: UNKNOWN
Keywords: ASD ViewSpecPro RS3 spectroscopy automation
Platform: UNKNOWN
Classifier: Development Status :: 3 - Alpha
Classifier: Programming Language :: Python :: 3
Requires-Python: >=3
Requires-Dist: pywinauto
Requires-Dist: pyautogui
